README.md
setup.py
dbunit/__init__.py
dbunit/dbunit.py
dbunit/utils.py
dbunit.egg-info/PKG-INFO
dbunit.egg-info/SOURCES.txt
dbunit.egg-info/dependency_links.txt
dbunit.egg-info/requires.txt
dbunit.egg-info/top_level.txt
test_dbunit/__init__.py
test_dbunit/test_dbunit.py
test_dbunit/test_hi.py