Metadata-Version: 2.1
Name: dbunit
Version: 0.2
Summary: Python写的一个仿Java DbUnit的数据库单元测试工具
Home-page: https://github.com/shwdbd/dbunit
Author: Wang Junjie
Author-email: shwangjj@163.com
Maintainer: Wang Junjie
Maintainer-email: shwanjj@163.com
License: BSD License
Platform: all
Classifier: Programming Language :: Python :: 3.7
Classifier: Programming Language :: Python :: 3.8
Requires-Python: >=3.7
